Metadata-Version: 2.1
Name: b-perfume-scraper
Version: 0.0.0
Summary: A package that retrieves image and text data about perfumes on the Bloom Perfumery website
Home-page: https://github.com/emm-sam/Data-Collection-Pipeline
Author: Emma Samouelle
License: MIT
Platform: UNKNOWN
License-File: LICENSE
